{
  "formatVersion": 1,
  "database": {
    "version": 12,
    "identityHash": "c75ecfcf1e01037efc8ad518e17c50a3",
    "entities": [
      {
        "tableName": "characters",
        "createSql": "CREATE TABLE IF NOT EXISTS `${TABLE_NAME}` (`id` TEXT NOT NULL, `name` TEXT NOT NULL, `displayName` TEXT, `shortDescription` TEXT, `longDescription` TEXT, `persona` TEXT, `backstory` TEXT, `greeting` TEXT, `avatarUrl` TEXT, `avatar_video_url` TEXT, `appearance` TEXT, `personality` TEXT, `scenario` TEXT, `exampleDialogue` TEXT, `characterBook` TEXT, `temperature` REAL NOT NULL, `topP` REAL NOT NULL, `maxTokens` INTEGER NOT NULL, `nsfwEnabled` INTEGER NOT NULL, `tags` TEXT, `categories` TEXT, `creatorId` TEXT, `creator` TEXT, `creatorNotes` TEXT, `characterVersion` TEXT NOT NULL, `isPublic` INTEGER NOT NULL, `isFeatured` INTEGER NOT NULL, `isFavorite` INTEGER NOT NULL, `description` TEXT, `stats` TEXT, `version` INTEGER NOT NULL, `totalMessages` INTEGER NOT NULL, `totalConversations` INTEGER NOT NULL, `averageRating` REAL NOT NULL, `totalRatings` INTEGER NOT NULL, `lastInteraction` TEXT, `isActive` INTEGER NOT NULL, `dynamicStatsEnabled` INTEGER NOT NULL, PRIMARY KEY(`id`))",
        "fields": [
          {
            "fieldPath": "id",
            "columnName": "id",
            "affinity": "TEXT",
            "notNull": true
          },
          {
            "fieldPath": "name",
            "columnName": "name",
            "affinity": "TEXT",
            "notNull": true
          },
          {
            "fieldPath": "displayName",
            "columnName": "displayName",
            "affinity": "TEXT",
            "notNull": false
          },
          {
            "fieldPath": "shortDescription",
            "columnName": "shortDescription",
            "affinity": "TEXT",
            "notNull": false
          },
          {
            "fieldPath": "longDescription",
            "columnName": "longDescription",
            "affinity": "TEXT",
            "notNull": false
          },
          {
            "fieldPath": "persona",
            "columnName": "persona",
            "affinity": "TEXT",
            "notNull": false
          },
          {
            "fieldPath": "backstory",
            "columnName": "backstory",
            "affinity": "TEXT",
            "notNull": false
          },
          {
            "fieldPath": "greeting",
            "columnName": "greeting",
            "affinity": "TEXT",
            "notNull": false
          },
          {
            "fieldPath": "avatarUrl",
            "columnName": "avatarUrl",
            "affinity": "TEXT",
            "notNull": false
          },
          {
            "fieldPath": "avatarVideoUrl",
            "columnName": "avatar_video_url",
            "affinity": "TEXT",
            "notNull": false
          },
          {
            "fieldPath": "appearance",
            "columnName": "appearance",
            "affinity": "TEXT",
            "notNull": false
          },
          {
            "fieldPath": "personality",
            "columnName": "personality",
            "affinity": "TEXT",
            "notNull": false
          },
          {
            "fieldPath": "scenario",
            "columnName": "scenario",
            "affinity": "TEXT",
            "notNull": false
          },
          {
            "fieldPath": "exampleDialogue",
            "columnName": "exampleDialogue",
            "affinity": "TEXT",
            "notNull": false
          },
          {
            "fieldPath": "characterBook",
            "columnName": "characterBook",
            "affinity": "TEXT",
            "notNull": false
          },
          {
            "fieldPath": "temperature",
            "columnName": "temperature",
            "affinity": "REAL",
            "notNull": true
          },
          {
            "fieldPath": "topP",
            "columnName": "topP",
            "affinity": "REAL",
            "notNull": true
          },
          {
            "fieldPath": "maxTokens",
            "columnName": "maxTokens",
            "affinity": "INTEGER",
            "notNull": true
          },
          {
            "fieldPath": "nsfwEnabled",
            "columnName": "nsfwEnabled",
            "affinity": "INTEGER",
            "notNull": true
          },
          {
            "fieldPath": "tags",
            "columnName": "tags",
            "affinity": "TEXT",
            "notNull": false
          },
          {
            "fieldPath": "categories",
            "columnName": "categories",
            "affinity": "TEXT",
            "notNull": false
          },
          {
            "fieldPath": "creatorId",
            "columnName": "creatorId",
            "affinity": "TEXT",
            "notNull": false
          },
          {
            "fieldPath": "creator",
            "columnName": "creator",
            "affinity": "TEXT",
            "notNull": false
          },
          {
            "fieldPath": "creatorNotes",
            "columnName": "creatorNotes",
            "affinity": "TEXT",
            "notNull": false
          },
          {
            "fieldPath": "characterVersion",
            "columnName": "characterVersion",
            "affinity": "TEXT",
            "notNull": true
          },
          {
            "fieldPath": "isPublic",
            "columnName": "isPublic",
            "affinity": "INTEGER",
            "notNull": true
          },
          {
            "fieldPath": "isFeatured",
            "columnName": "isFeatured",
            "affinity": "INTEGER",
            "notNull": true
          },
          {
            "fieldPath": "isFavorite",
            "columnName": "isFavorite",
            "affinity": "INTEGER",
            "notNull": true
          },
          {
            "fieldPath": "description",
            "columnName": "description",
            "affinity": "TEXT",
            "notNull": false
          },
          {
            "fieldPath": "stats",
            "columnName": "stats",
            "affinity": "TEXT",
            "notNull": false
          },
          {
            "fieldPath": "version",
            "columnName": "version",
            "affinity": "INTEGER",
            "notNull": true
          },
          {
            "fieldPath": "totalMessages",
            "columnName": "totalMessages",
            "affinity": "INTEGER",
            "notNull": true
          },
          {
            "fieldPath": "totalConversations",
            "columnName": "totalConversations",
            "affinity": "INTEGER",
            "notNull": true
          },
          {
            "fieldPath": "averageRating",
            "columnName": "averageRating",
            "affinity": "REAL",
            "notNull": true
          },
          {
            "fieldPath": "totalRatings",
            "columnName": "totalRatings",
            "affinity": "INTEGER",
            "notNull": true
          },
          {
            "fieldPath": "lastInteraction",
            "columnName": "lastInteraction",
            "affinity": "TEXT",
            "notNull": false
          },
          {
            "fieldPath": "isActive",
            "columnName": "isActive",
            "affinity": "INTEGER",
            "notNull": true
          },
          {
            "fieldPath": "dynamicStatsEnabled",
            "columnName": "dynamicStatsEnabled",
            "affinity": "INTEGER",
            "notNull": true
          }
        ],
        "primaryKey": {
          "autoGenerate": false,
          "columnNames": [
            "id"
          ]
        },
        "indices": [
          {
            "name": "index_characters_name",
            "unique": false,
            "columnNames": [
              "name"
            ],
            "orders": [],
            "createSql": "CREATE INDEX IF NOT EXISTS `index_characters_name` ON `${TABLE_NAME}` (`name`)"
          },
          {
            "name": "index_characters_isActive",
            "unique": false,
            "columnNames": [
              "isActive"
            ],
            "orders": [],
            "createSql": "CREATE INDEX IF NOT EXISTS `index_characters_isActive` ON `${TABLE_NAME}` (`isActive`)"
          },
          {
            "name": "index_characters_isPublic",
            "unique": false,
            "columnNames": [
              "isPublic"
            ],
            "orders": [],
            "createSql": "CREATE INDEX IF NOT EXISTS `index_characters_isPublic` ON `${TABLE_NAME}` (`isPublic`)"
          },
          {
            "name": "index_characters_totalMessages",
            "unique": false,
            "columnNames": [
              "totalMessages"
            ],
            "orders": [],
            "createSql": "CREATE INDEX IF NOT EXISTS `index_characters_totalMessages` ON `${TABLE_NAME}` (`totalMessages`)"
          },
          {
            "name": "index_characters_averageRating",
            "unique": false,
            "columnNames": [
              "averageRating"
            ],
            "orders": [],
            "createSql": "CREATE INDEX IF NOT EXISTS `index_characters_averageRating` ON `${TABLE_NAME}` (`averageRating`)"
          }
        ],
        "foreignKeys": []
      },
      {
        "tableName": "conversations",
        "createSql": "CREATE TABLE IF NOT EXISTS `${TABLE_NAME}` (`id` TEXT NOT NULL, `title` TEXT, `characterId` TEXT NOT NULL, `characterName` TEXT NOT NULL, `userId` TEXT, `isActive` INTEGER NOT NULL, `isArchived` INTEGER NOT NULL, `isFavorite` INTEGER NOT NULL, `totalMessages` INTEGER NOT NULL, `userMessages` INTEGER NOT NULL, `characterMessages` INTEGER NOT NULL, `createdAt` INTEGER NOT NULL, `updatedAt` INTEGER NOT NULL, `lastMessageAt` INTEGER, PRIMARY KEY(`id`), FOREIGN KEY(`characterId`) REFERENCES `characters`(`id`) ON UPDATE NO ACTION ON DELETE CASCADE )",
        "fields": [
          {
            "fieldPath": "id",
            "columnName": "id",
            "affinity": "TEXT",
            "notNull": true
          },
          {
            "fieldPath": "title",
            "columnName": "title",
            "affinity": "TEXT",
            "notNull": false
          },
          {
            "fieldPath": "characterId",
            "columnName": "characterId",
            "affinity": "TEXT",
            "notNull": true
          },
          {
            "fieldPath": "characterName",
            "columnName": "characterName",
            "affinity": "TEXT",
            "notNull": true
          },
          {
            "fieldPath": "userId",
            "columnName": "userId",
            "affinity": "TEXT",
            "notNull": false
          },
          {
            "fieldPath": "isActive",
            "columnName": "isActive",
            "affinity": "INTEGER",
            "notNull": true
          },
          {
            "fieldPath": "isArchived",
            "columnName": "isArchived",
            "affinity": "INTEGER",
            "notNull": true
          },
          {
            "fieldPath": "isFavorite",
            "columnName": "isFavorite",
            "affinity": "INTEGER",
            "notNull": true
          },
          {
            "fieldPath": "totalMessages",
            "columnName": "totalMessages",
            "affinity": "INTEGER",
            "notNull": true
          },
          {
            "fieldPath": "userMessages",
            "columnName": "userMessages",
            "affinity": "INTEGER",
            "notNull": true
          },
          {
            "fieldPath": "characterMessages",
            "columnName": "characterMessages",
            "affinity": "INTEGER",
            "notNull": true
          },
          {
            "fieldPath": "createdAt",
            "columnName": "createdAt",
            "affinity": "INTEGER",
            "notNull": true
          },
          {
            "fieldPath": "updatedAt",
            "columnName": "updatedAt",
            "affinity": "INTEGER",
            "notNull": true
          },
          {
            "fieldPath": "lastMessageAt",
            "columnName": "lastMessageAt",
            "affinity": "INTEGER",
            "notNull": false
          }
        ],
        "primaryKey": {
          "autoGenerate": false,
          "columnNames": [
            "id"
          ]
        },
        "indices": [
          {
            "name": "index_conversations_characterId",
            "unique": false,
            "columnNames": [
              "characterId"
            ],
            "orders": [],
            "createSql": "CREATE INDEX IF NOT EXISTS `index_conversations_characterId` ON `${TABLE_NAME}` (`characterId`)"
          },
          {
            "name": "index_conversations_userId",
            "unique": false,
            "columnNames": [
              "userId"
            ],
            "orders": [],
            "createSql": "CREATE INDEX IF NOT EXISTS `index_conversations_userId` ON `${TABLE_NAME}` (`userId`)"
          },
          {
            "name": "index_conversations_isActive",
            "unique": false,
            "columnNames": [
              "isActive"
            ],
            "orders": [],
            "createSql": "CREATE INDEX IF NOT EXISTS `index_conversations_isActive` ON `${TABLE_NAME}` (`isActive`)"
          },
          {
            "name": "index_conversations_lastMessageAt",
            "unique": false,
            "columnNames": [
              "lastMessageAt"
            ],
            "orders": [],
            "createSql": "CREATE INDEX IF NOT EXISTS `index_conversations_lastMessageAt` ON `${TABLE_NAME}` (`lastMessageAt`)"
          },
          {
            "name": "index_conversations_createdAt",
            "unique": false,
            "columnNames": [
              "createdAt"
            ],
            "orders": [],
            "createSql": "CREATE INDEX IF NOT EXISTS `index_conversations_createdAt` ON `${TABLE_NAME}` (`createdAt`)"
          }
        ],
        "foreignKeys": [
          {
            "table": "characters",
            "onDelete": "CASCADE",
            "onUpdate": "NO ACTION",
            "columns": [
              "characterId"
            ],
            "referencedColumns": [
              "id"
            ]
          }
        ]
      },
      {
        "tableName": "messages",
        "createSql": "CREATE TABLE IF NOT EXISTS `${TABLE_NAME}` (`id` TEXT NOT NULL, `conversationId` TEXT NOT NULL, `content` TEXT NOT NULL, `role` TEXT NOT NULL, `senderType` TEXT, `timestamp` INTEGER NOT NULL, `characterId` TEXT, `characterName` TEXT, `userId` TEXT, `isEdited` INTEGER NOT NULL, `createdAt` INTEGER NOT NULL, `updatedAt` INTEGER NOT NULL, `messageType` TEXT NOT NULL, `metadataJson` TEXT, PRIMARY KEY(`id`), FOREIGN KEY(`conversationId`) REFERENCES `conversations`(`id`) ON UPDATE NO ACTION ON DELETE CASCADE )",
        "fields": [
          {
            "fieldPath": "id",
            "columnName": "id",
            "affinity": "TEXT",
            "notNull": true
          },
          {
            "fieldPath": "conversationId",
            "columnName": "conversationId",
            "affinity": "TEXT",
            "notNull": true
          },
          {
            "fieldPath": "content",
            "columnName": "content",
            "affinity": "TEXT",
            "notNull": true
          },
          {
            "fieldPath": "role",
            "columnName": "role",
            "affinity": "TEXT",
            "notNull": true
          },
          {
            "fieldPath": "senderType",
            "columnName": "senderType",
            "affinity": "TEXT",
            "notNull": false
          },
          {
            "fieldPath": "timestamp",
            "columnName": "timestamp",
            "affinity": "INTEGER",
            "notNull": true
          },
          {
            "fieldPath": "characterId",
            "columnName": "characterId",
            "affinity": "TEXT",
            "notNull": false
          },
          {
            "fieldPath": "characterName",
            "columnName": "characterName",
            "affinity": "TEXT",
            "notNull": false
          },
          {
            "fieldPath": "userId",
            "columnName": "userId",
            "affinity": "TEXT",
            "notNull": false
          },
          {
            "fieldPath": "isEdited",
            "columnName": "isEdited",
            "affinity": "INTEGER",
            "notNull": true
          },
          {
            "fieldPath": "createdAt",
            "columnName": "createdAt",
            "affinity": "INTEGER",
            "notNull": true
          },
          {
            "fieldPath": "updatedAt",
            "columnName": "updatedAt",
            "affinity": "INTEGER",
            "notNull": true
          },
          {
            "fieldPath": "messageType",
            "columnName": "messageType",
            "affinity": "TEXT",
            "notNull": true
          },
          {
            "fieldPath": "metadataJson",
            "columnName": "metadataJson",
            "affinity": "TEXT",
            "notNull": false
          }
        ],
        "primaryKey": {
          "autoGenerate": false,
          "columnNames": [
            "id"
          ]
        },
        "indices": [
          {
            "name": "index_messages_conversationId",
            "unique": false,
            "columnNames": [
              "conversationId"
            ],
            "orders": [],
            "createSql": "CREATE INDEX IF NOT EXISTS `index_messages_conversationId` ON `${TABLE_NAME}` (`conversationId`)"
          },
          {
            "name": "index_messages_role",
            "unique": false,
            "columnNames": [
              "role"
            ],
            "orders": [],
            "createSql": "CREATE INDEX IF NOT EXISTS `index_messages_role` ON `${TABLE_NAME}` (`role`)"
          },
          {
            "name": "index_messages_createdAt",
            "unique": false,
            "columnNames": [
              "createdAt"
            ],
            "orders": [],
            "createSql": "CREATE INDEX IF NOT EXISTS `index_messages_createdAt` ON `${TABLE_NAME}` (`createdAt`)"
          }
        ],
        "foreignKeys": [
          {
            "table": "conversations",
            "onDelete": "CASCADE",
            "onUpdate": "NO ACTION",
            "columns": [
              "conversationId"
            ],
            "referencedColumns": [
              "id"
            ]
          }
        ]
      },
      {
        "tableName": "users",
        "createSql": "CREATE TABLE IF NOT EXISTS `${TABLE_NAME}` (`id` TEXT NOT NULL, `username` TEXT NOT NULL, `email` TEXT, `displayName` TEXT, `avatarUrl` TEXT, `isPremium` INTEGER NOT NULL, `preferences` TEXT, `totalMessages` INTEGER NOT NULL, `totalConversations` INTEGER NOT NULL, `createdAt` INTEGER NOT NULL, `updatedAt` INTEGER NOT NULL, `isActive` INTEGER NOT NULL, PRIMARY KEY(`id`))",
        "fields": [
          {
            "fieldPath": "id",
            "columnName": "id",
            "affinity": "TEXT",
            "notNull": true
          },
          {
            "fieldPath": "username",
            "columnName": "username",
            "affinity": "TEXT",
            "notNull": true
          },
          {
            "fieldPath": "email",
            "columnName": "email",
            "affinity": "TEXT",
            "notNull": false
          },
          {
            "fieldPath": "displayName",
            "columnName": "displayName",
            "affinity": "TEXT",
            "notNull": false
          },
          {
            "fieldPath": "avatarUrl",
            "columnName": "avatarUrl",
            "affinity": "TEXT",
            "notNull": false
          },
          {
            "fieldPath": "isPremium",
            "columnName": "isPremium",
            "affinity": "INTEGER",
            "notNull": true
          },
          {
            "fieldPath": "preferences",
            "columnName": "preferences",
            "affinity": "TEXT",
            "notNull": false
          },
          {
            "fieldPath": "totalMessages",
            "columnName": "totalMessages",
            "affinity": "INTEGER",
            "notNull": true
          },
          {
            "fieldPath": "totalConversations",
            "columnName": "totalConversations",
            "affinity": "INTEGER",
            "notNull": true
          },
          {
            "fieldPath": "createdAt",
            "columnName": "createdAt",
            "affinity": "INTEGER",
            "notNull": true
          },
          {
            "fieldPath": "updatedAt",
            "columnName": "updatedAt",
            "affinity": "INTEGER",
            "notNull": true
          },
          {
            "fieldPath": "isActive",
            "columnName": "isActive",
            "affinity": "INTEGER",
            "notNull": true
          }
        ],
        "primaryKey": {
          "autoGenerate": false,
          "columnNames": [
            "id"
          ]
        },
        "indices": [
          {
            "name": "index_users_username",
            "unique": true,
            "columnNames": [
              "username"
            ],
            "orders": [],
            "createSql": "CREATE UNIQUE INDEX IF NOT EXISTS `index_users_username` ON `${TABLE_NAME}` (`username`)"
          },
          {
            "name": "index_users_isActive",
            "unique": false,
            "columnNames": [
              "isActive"
            ],
            "orders": [],
            "createSql": "CREATE INDEX IF NOT EXISTS `index_users_isActive` ON `${TABLE_NAME}` (`isActive`)"
          }
        ],
        "foreignKeys": []
      },
      {
        "tableName": "user_sessions",
        "createSql": "CREATE TABLE IF NOT EXISTS `${TABLE_NAME}` (`id` TEXT NOT NULL, `userId` TEXT NOT NULL, `sessionToken` TEXT NOT NULL, `deviceInfo` TEXT, `isActive` INTEGER NOT NULL, `expiresAt` INTEGER NOT NULL, `createdAt` INTEGER NOT NULL, `lastAccessedAt` INTEGER NOT NULL, PRIMARY KEY(`id`), FOREIGN KEY(`userId`) REFERENCES `users`(`id`) ON UPDATE NO ACTION ON DELETE CASCADE )",
        "fields": [
          {
            "fieldPath": "id",
            "columnName": "id",
            "affinity": "TEXT",
            "notNull": true
          },
          {
            "fieldPath": "userId",
            "columnName": "userId",
            "affinity": "TEXT",
            "notNull": true
          },
          {
            "fieldPath": "sessionToken",
            "columnName": "sessionToken",
            "affinity": "TEXT",
            "notNull": true
          },
          {
            "fieldPath": "deviceInfo",
            "columnName": "deviceInfo",
            "affinity": "TEXT",
            "notNull": false
          },
          {
            "fieldPath": "isActive",
            "columnName": "isActive",
            "affinity": "INTEGER",
            "notNull": true
          },
          {
            "fieldPath": "expiresAt",
            "columnName": "expiresAt",
            "affinity": "INTEGER",
            "notNull": true
          },
          {
            "fieldPath": "createdAt",
            "columnName": "createdAt",
            "affinity": "INTEGER",
            "notNull": true
          },
          {
            "fieldPath": "lastAccessedAt",
            "columnName": "lastAccessedAt",
            "affinity": "INTEGER",
            "notNull": true
          }
        ],
        "primaryKey": {
          "autoGenerate": false,
          "columnNames": [
            "id"
          ]
        },
        "indices": [
          {
            "name": "index_user_sessions_userId",
            "unique": false,
            "columnNames": [
              "userId"
            ],
            "orders": [],
            "createSql": "CREATE INDEX IF NOT EXISTS `index_user_sessions_userId` ON `${TABLE_NAME}` (`userId`)"
          },
          {
            "name": "index_user_sessions_sessionToken",
            "unique": true,
            "columnNames": [
              "sessionToken"
            ],
            "orders": [],
            "createSql": "CREATE UNIQUE INDEX IF NOT EXISTS `index_user_sessions_sessionToken` ON `${TABLE_NAME}` (`sessionToken`)"
          },
          {
            "name": "index_user_sessions_isActive",
            "unique": false,
            "columnNames": [
              "isActive"
            ],
            "orders": [],
            "createSql": "CREATE INDEX IF NOT EXISTS `index_user_sessions_isActive` ON `${TABLE_NAME}` (`isActive`)"
          }
        ],
        "foreignKeys": [
          {
            "table": "users",
            "onDelete": "CASCADE",
            "onUpdate": "NO ACTION",
            "columns": [
              "userId"
            ],
            "referencedColumns": [
              "id"
            ]
          }
        ]
      },
      {
        "tableName": "generated_images",
        "createSql": "CREATE TABLE IF NOT EXISTS `${TABLE_NAME}` (`id` TEXT NOT NULL, `prompt` TEXT NOT NULL, `localPath` TEXT NOT NULL, `model` TEXT, `generationTime` INTEGER NOT NULL, `size` TEXT NOT NULL, `timestamp` INTEGER NOT NULL, PRIMARY KEY(`id`))",
        "fields": [
          {
            "fieldPath": "id",
            "columnName": "id",
            "affinity": "TEXT",
            "notNull": true
          },
          {
            "fieldPath": "prompt",
            "columnName": "prompt",
            "affinity": "TEXT",
            "notNull": true
          },
          {
            "fieldPath": "localPath",
            "columnName": "localPath",
            "affinity": "TEXT",
            "notNull": true
          },
          {
            "fieldPath": "model",
            "columnName": "model",
            "affinity": "TEXT",
            "notNull": false
          },
          {
            "fieldPath": "generationTime",
            "columnName": "generationTime",
            "affinity": "INTEGER",
            "notNull": true
          },
          {
            "fieldPath": "size",
            "columnName": "size",
            "affinity": "TEXT",
            "notNull": true
          },
          {
            "fieldPath": "timestamp",
            "columnName": "timestamp",
            "affinity": "INTEGER",
            "notNull": true
          }
        ],
        "primaryKey": {
          "autoGenerate": false,
          "columnNames": [
            "id"
          ]
        },
        "indices": [],
        "foreignKeys": []
      },
      {
        "tableName": "chat_image_settings",
        "createSql": "CREATE TABLE IF NOT EXISTS `${TABLE_NAME}` (`chatId` TEXT NOT NULL, `inputImageOption` TEXT NOT NULL, `localImagePath` TEXT, `cloudImageUrl` TEXT, `useCharacterAvatar` INTEGER NOT NULL, `predictionCreationMethod` TEXT NOT NULL, `manualPredictionInput` TEXT, `createdAt` INTEGER NOT NULL, `updatedAt` INTEGER NOT NULL, PRIMARY KEY(`chatId`))",
        "fields": [
          {
            "fieldPath": "chatId",
            "columnName": "chatId",
            "affinity": "TEXT",
            "notNull": true
          },
          {
            "fieldPath": "inputImageOption",
            "columnName": "inputImageOption",
            "affinity": "TEXT",
            "notNull": true
          },
          {
            "fieldPath": "localImagePath",
            "columnName": "localImagePath",
            "affinity": "TEXT",
            "notNull": false
          },
          {
            "fieldPath": "cloudImageUrl",
            "columnName": "cloudImageUrl",
            "affinity": "TEXT",
            "notNull": false
          },
          {
            "fieldPath": "useCharacterAvatar",
            "columnName": "useCharacterAvatar",
            "affinity": "INTEGER",
            "notNull": true
          },
          {
            "fieldPath": "predictionCreationMethod",
            "columnName": "predictionCreationMethod",
            "affinity": "TEXT",
            "notNull": true
          },
          {
            "fieldPath": "manualPredictionInput",
            "columnName": "manualPredictionInput",
            "affinity": "TEXT",
            "notNull": false
          },
          {
            "fieldPath": "createdAt",
            "columnName": "createdAt",
            "affinity": "INTEGER",
            "notNull": true
          },
          {
            "fieldPath": "updatedAt",
            "columnName": "updatedAt",
            "affinity": "INTEGER",
            "notNull": true
          }
        ],
        "primaryKey": {
          "autoGenerate": false,
          "columnNames": [
            "chatId"
          ]
        },
        "indices": [],
        "foreignKeys": []
      },
      {
        "tableName": "accounts",
        "createSql": "CREATE TABLE IF NOT EXISTS `${TABLE_NAME}` (`id` TEXT NOT NULL, `username` TEXT NOT NULL, `email` TEXT, `fullName` TEXT, `dateOfBirth` TEXT, `avatarUrl` TEXT, `isPremium` INTEGER NOT NULL, `accessToken` TEXT, `refreshToken` TEXT, `createdAt` INTEGER NOT NULL, `updatedAt` INTEGER NOT NULL, PRIMARY KEY(`id`))",
        "fields": [
          {
            "fieldPath": "id",
            "columnName": "id",
            "affinity": "TEXT",
            "notNull": true
          },
          {
            "fieldPath": "username",
            "columnName": "username",
            "affinity": "TEXT",
            "notNull": true
          },
          {
            "fieldPath": "email",
            "columnName": "email",
            "affinity": "TEXT",
            "notNull": false
          },
          {
            "fieldPath": "fullName",
            "columnName": "fullName",
            "affinity": "TEXT",
            "notNull": false
          },
          {
            "fieldPath": "dateOfBirth",
            "columnName": "dateOfBirth",
            "affinity": "TEXT",
            "notNull": false
          },
          {
            "fieldPath": "avatarUrl",
            "columnName": "avatarUrl",
            "affinity": "TEXT",
            "notNull": false
          },
          {
            "fieldPath": "isPremium",
            "columnName": "isPremium",
            "affinity": "INTEGER",
            "notNull": true
          },
          {
            "fieldPath": "accessToken",
            "columnName": "accessToken",
            "affinity": "TEXT",
            "notNull": false
          },
          {
            "fieldPath": "refreshToken",
            "columnName": "refreshToken",
            "affinity": "TEXT",
            "notNull": false
          },
          {
            "fieldPath": "createdAt",
            "columnName": "createdAt",
            "affinity": "INTEGER",
            "notNull": true
          },
          {
            "fieldPath": "updatedAt",
            "columnName": "updatedAt",
            "affinity": "INTEGER",
            "notNull": true
          }
        ],
        "primaryKey": {
          "autoGenerate": false,
          "columnNames": [
            "id"
          ]
        },
        "indices": [],
        "foreignKeys": []
      },
      {
        "tableName": "custom_api_providers",
        "createSql": "CREATE TABLE IF NOT EXISTS `${TABLE_NAME}` (`id` TEXT NOT NULL, `name` TEXT NOT NULL, `type` TEXT NOT NULL, `baseUrl` TEXT NOT NULL, `apiKey` TEXT NOT NULL, `isEnabled` INTEGER NOT NULL, `createdAt` INTEGER NOT NULL, `updatedAt` INTEGER NOT NULL, PRIMARY KEY(`id`))",
        "fields": [
          {
            "fieldPath": "id",
            "columnName": "id",
            "affinity": "TEXT",
            "notNull": true
          },
          {
            "fieldPath": "name",
            "columnName": "name",
            "affinity": "TEXT",
            "notNull": true
          },
          {
            "fieldPath": "type",
            "columnName": "type",
            "affinity": "TEXT",
            "notNull": true
          },
          {
            "fieldPath": "baseUrl",
            "columnName": "baseUrl",
            "affinity": "TEXT",
            "notNull": true
          },
          {
            "fieldPath": "apiKey",
            "columnName": "apiKey",
            "affinity": "TEXT",
            "notNull": true
          },
          {
            "fieldPath": "isEnabled",
            "columnName": "isEnabled",
            "affinity": "INTEGER",
            "notNull": true
          },
          {
            "fieldPath": "createdAt",
            "columnName": "createdAt",
            "affinity": "INTEGER",
            "notNull": true
          },
          {
            "fieldPath": "updatedAt",
            "columnName": "updatedAt",
            "affinity": "INTEGER",
            "notNull": true
          }
        ],
        "primaryKey": {
          "autoGenerate": false,
          "columnNames": [
            "id"
          ]
        },
        "indices": [
          {
            "name": "index_custom_api_providers_type",
            "unique": false,
            "columnNames": [
              "type"
            ],
            "orders": [],
            "createSql": "CREATE INDEX IF NOT EXISTS `index_custom_api_providers_type` ON `${TABLE_NAME}` (`type`)"
          }
        ],
        "foreignKeys": []
      },
      {
        "tableName": "custom_api_endpoints",
        "createSql": "CREATE TABLE IF NOT EXISTS `${TABLE_NAME}` (`id` TEXT NOT NULL, `providerId` TEXT NOT NULL, `endpointPath` TEXT NOT NULL, `httpMethod` TEXT NOT NULL, `requestSchemaJson` TEXT NOT NULL, `responseSchemaJson` TEXT NOT NULL, `purpose` TEXT NOT NULL, `createdAt` INTEGER NOT NULL, PRIMARY KEY(`id`), FOREIGN KEY(`providerId`) REFERENCES `custom_api_providers`(`id`) ON UPDATE NO ACTION ON DELETE CASCADE )",
        "fields": [
          {
            "fieldPath": "id",
            "columnName": "id",
            "affinity": "TEXT",
            "notNull": true
          },
          {
            "fieldPath": "providerId",
            "columnName": "providerId",
            "affinity": "TEXT",
            "notNull": true
          },
          {
            "fieldPath": "endpointPath",
            "columnName": "endpointPath",
            "affinity": "TEXT",
            "notNull": true
          },
          {
            "fieldPath": "httpMethod",
            "columnName": "httpMethod",
            "affinity": "TEXT",
            "notNull": true
          },
          {
            "fieldPath": "requestSchemaJson",
            "columnName": "requestSchemaJson",
            "affinity": "TEXT",
            "notNull": true
          },
          {
            "fieldPath": "responseSchemaJson",
            "columnName": "responseSchemaJson",
            "affinity": "TEXT",
            "notNull": true
          },
          {
            "fieldPath": "purpose",
            "columnName": "purpose",
            "affinity": "TEXT",
            "notNull": true
          },
          {
            "fieldPath": "createdAt",
            "columnName": "createdAt",
            "affinity": "INTEGER",
            "notNull": true
          }
        ],
        "primaryKey": {
          "autoGenerate": false,
          "columnNames": [
            "id"
          ]
        },
        "indices": [
          {
            "name": "index_custom_api_endpoints_providerId",
            "unique": false,
            "columnNames": [
              "providerId"
            ],
            "orders": [],
            "createSql": "CREATE INDEX IF NOT EXISTS `index_custom_api_endpoints_providerId` ON `${TABLE_NAME}` (`providerId`)"
          }
        ],
        "foreignKeys": [
          {
            "table": "custom_api_providers",
            "onDelete": "CASCADE",
            "onUpdate": "NO ACTION",
            "columns": [
              "providerId"
            ],
            "referencedColumns": [
              "id"
            ]
          }
        ]
      },
      {
        "tableName": "custom_api_models",
        "createSql": "CREATE TABLE IF NOT EXISTS `${TABLE_NAME}` (`id` TEXT NOT NULL, `providerId` TEXT NOT NULL, `modelId` TEXT NOT NULL, `displayName` TEXT NOT NULL, `capabilitiesJson` TEXT NOT NULL, `isActive` INTEGER NOT NULL, `createdAt` INTEGER NOT NULL, PRIMARY KEY(`id`), FOREIGN KEY(`providerId`) REFERENCES `custom_api_providers`(`id`) ON UPDATE NO ACTION ON DELETE CASCADE )",
        "fields": [
          {
            "fieldPath": "id",
            "columnName": "id",
            "affinity": "TEXT",
            "notNull": true
          },
          {
            "fieldPath": "providerId",
            "columnName": "providerId",
            "affinity": "TEXT",
            "notNull": true
          },
          {
            "fieldPath": "modelId",
            "columnName": "modelId",
            "affinity": "TEXT",
            "notNull": true
          },
          {
            "fieldPath": "displayName",
            "columnName": "displayName",
            "affinity": "TEXT",
            "notNull": true
          },
          {
            "fieldPath": "capabilitiesJson",
            "columnName": "capabilitiesJson",
            "affinity": "TEXT",
            "notNull": true
          },
          {
            "fieldPath": "isActive",
            "columnName": "isActive",
            "affinity": "INTEGER",
            "notNull": true
          },
          {
            "fieldPath": "createdAt",
            "columnName": "createdAt",
            "affinity": "INTEGER",
            "notNull": true
          }
        ],
        "primaryKey": {
          "autoGenerate": false,
          "columnNames": [
            "id"
          ]
        },
        "indices": [
          {
            "name": "index_custom_api_models_providerId",
            "unique": false,
            "columnNames": [
              "providerId"
            ],
            "orders": [],
            "createSql": "CREATE INDEX IF NOT EXISTS `index_custom_api_models_providerId` ON `${TABLE_NAME}` (`providerId`)"
          }
        ],
        "foreignKeys": [
          {
            "table": "custom_api_providers",
            "onDelete": "CASCADE",
            "onUpdate": "NO ACTION",
            "columns": [
              "providerId"
            ],
            "referencedColumns": [
              "id"
            ]
          }
        ]
      },
      {
        "tableName": "custom_api_parameters",
        "createSql": "CREATE TABLE IF NOT EXISTS `${TABLE_NAME}` (`id` TEXT NOT NULL, `modelId` TEXT NOT NULL, `paramName` TEXT NOT NULL, `paramType` TEXT NOT NULL, `defaultValue` TEXT, `minValue` TEXT, `maxValue` TEXT, `isRequired` INTEGER NOT NULL, `description` TEXT, PRIMARY KEY(`id`), FOREIGN KEY(`modelId`) REFERENCES `custom_api_models`(`id`) ON UPDATE NO ACTION ON DELETE CASCADE )",
        "fields": [
          {
            "fieldPath": "id",
            "columnName": "id",
            "affinity": "TEXT",
            "notNull": true
          },
          {
            "fieldPath": "modelId",
            "columnName": "modelId",
            "affinity": "TEXT",
            "notNull": true
          },
          {
            "fieldPath": "paramName",
            "columnName": "paramName",
            "affinity": "TEXT",
            "notNull": true
          },
          {
            "fieldPath": "paramType",
            "columnName": "paramType",
            "affinity": "TEXT",
            "notNull": true
          },
          {
            "fieldPath": "defaultValue",
            "columnName": "defaultValue",
            "affinity": "TEXT",
            "notNull": false
          },
          {
            "fieldPath": "minValue",
            "columnName": "minValue",
            "affinity": "TEXT",
            "notNull": false
          },
          {
            "fieldPath": "maxValue",
            "columnName": "maxValue",
            "affinity": "TEXT",
            "notNull": false
          },
          {
            "fieldPath": "isRequired",
            "columnName": "isRequired",
            "affinity": "INTEGER",
            "notNull": true
          },
          {
            "fieldPath": "description",
            "columnName": "description",
            "affinity": "TEXT",
            "notNull": false
          }
        ],
        "primaryKey": {
          "autoGenerate": false,
          "columnNames": [
            "id"
          ]
        },
        "indices": [
          {
            "name": "index_custom_api_parameters_modelId",
            "unique": false,
            "columnNames": [
              "modelId"
            ],
            "orders": [],
            "createSql": "CREATE INDEX IF NOT EXISTS `index_custom_api_parameters_modelId` ON `${TABLE_NAME}` (`modelId`)"
          }
        ],
        "foreignKeys": [
          {
            "table": "custom_api_models",
            "onDelete": "CASCADE",
            "onUpdate": "NO ACTION",
            "columns": [
              "modelId"
            ],
            "referencedColumns": [
              "id"
            ]
          }
        ]
      },
      {
        "tableName": "custom_api_parameter_values",
        "createSql": "CREATE TABLE IF NOT EXISTS `${TABLE_NAME}` (`modelId` TEXT NOT NULL, `paramName` TEXT NOT NULL, `value` TEXT NOT NULL, `updatedAt` INTEGER NOT NULL, PRIMARY KEY(`modelId`, `paramName`), FOREIGN KEY(`modelId`) REFERENCES `custom_api_models`(`id`) ON UPDATE NO ACTION ON DELETE CASCADE )",
        "fields": [
          {
            "fieldPath": "modelId",
            "columnName": "modelId",
            "affinity": "TEXT",
            "notNull": true
          },
          {
            "fieldPath": "paramName",
            "columnName": "paramName",
            "affinity": "TEXT",
            "notNull": true
          },
          {
            "fieldPath": "value",
            "columnName": "value",
            "affinity": "TEXT",
            "notNull": true
          },
          {
            "fieldPath": "updatedAt",
            "columnName": "updatedAt",
            "affinity": "INTEGER",
            "notNull": true
          }
        ],
        "primaryKey": {
          "autoGenerate": false,
          "columnNames": [
            "modelId",
            "paramName"
          ]
        },
        "indices": [
          {
            "name": "index_custom_api_parameter_values_modelId",
            "unique": false,
            "columnNames": [
              "modelId"
            ],
            "orders": [],
            "createSql": "CREATE INDEX IF NOT EXISTS `index_custom_api_parameter_values_modelId` ON `${TABLE_NAME}` (`modelId`)"
          }
        ],
        "foreignKeys": [
          {
            "table": "custom_api_models",
            "onDelete": "CASCADE",
            "onUpdate": "NO ACTION",
            "columns": [
              "modelId"
            ],
            "referencedColumns": [
              "id"
            ]
          }
        ]
      }
    ],
    "views": [],
    "setupQueries": [
      "CREATE TABLE IF NOT EXISTS room_master_table (id INTEGER PRIMARY KEY,identity_hash TEXT)",
      "INSERT OR REPLACE INTO room_master_table (id,identity_hash) VALUES(42, 'c75ecfcf1e01037efc8ad518e17c50a3')"
    ]
  }
}